cprimefunc/__init__.py
cprimefunc/prime_checker.py
cprimefunc-0.1.dist-info/METADATA
cprimefunc-0.1.dist-info/WHEEL
cprimefunc-0.1.dist-info/top_level.txt
cprimefunc-0.1.dist-info/RECORD
