Metadata-Version: 2.1
Name: cprimefunc
Version: 0.1
Summary: A custom library for checking prime numbers
Author: Colourless-Chameleon
License: MIT
